{
  "data": [
    {
      "caller": "Ben",
      "start": "27.09.2013 02:00:19",
      "end": "27.09.2013 02:44:19",
      "duration": 44,
      "recipient": "Kimi",
      "origin": "South Dakota",
      "destination": "United Kingdom",
      "ratepermin": 0.07,
      "costs": 3.08,
      "origincontinent": "United States",
      "destinationcontinent": "Europe",
      "callergender": "Male",
      "recipientgender": "Female"
    },
    {
      "caller": "Ben",
      "start": "27.09.2013 02:02:36",
      "end": "27.09.2013 02:07:36",
      "duration": 5,
      "recipient": "Diana",
      "origin": "South Dakota",
      "destination": "Falkland Islands",
      "ratepermin": 0.45,
      "costs": 2.25,
      "origincontinent": "United States",
      "destinationcontinent": "South America",
      "callergender": "Male",
      "recipientgender": "Female"
    },
    {
      "caller": "Ben",
      "start": "27.09.2013 02:07:40",
      "end": "27.09.2013 02:30:40",
      "duration": 23,
      "recipient": "Diana",
      "origin": "South Dakota",
      "destination": "Falkland Islands",
      "ratepermin": 0.45,
      "costs": 10.35,
      "origincontinent": "United States",
      "destinationcontinent": "South America",
      "callergender": "Male",
      "recipientgender": "Female"
    },
    {
      "caller": "Leni",
      "start": "27.09.2013 02:11:39",
      "end": "27.09.2013 02:46:39",
      "duration": 35,
      "recipient": "Clemens",
      "origin": "Missouri",
      "destination": "Namibia",
      "ratepermin": 0.79,
      "costs": 27.65,
      "origincontinent": "United States",
      "destinationcontinent": "Africa",
      "callergender": "Male",
      "recipientgender": "Male"
    },
    {
      "caller": "Max",
      "start": "27.09.2013 02:13:26",
      "end": "27.09.2013 02:41:26",
      "duration": 28,
      "recipient": "Jasmin",
      "origin": "Ohio",
      "destination": "Mauritius",
      "ratepermin": 1.22,
      "costs": 34.16,
      "origincontinent": "United States",
      "destinationcontinent": "Africa",
      "callergender": "Male",
      "recipientgender": "Female"
    },
    {
      "caller": "Max",
      "start": "27.09.2013 02:14:06",
      "end": "27.09.2013 02:22:06",
      "duration": 8,
      "recipient": "Felina",
      "origin": "Ohio",
      "destination": "Suriname",
      "ratepermin": 1.22,
      "costs": 9.76,
      "origincontinent": "United States",
      "destinationcontinent": "South America",
      "callergender": "Male",
      "recipientgender": "Female"
    },
    {
      "caller": "Max",
      "start": "27.09.2013 02:14:26",
      "end": "27.09.2013 02:48:26",
      "duration": 34,
      "recipient": "Melinda",
      "origin": "Ohio",
      "destination": "Taiwan",
      "ratepermin": 0.07,
      "costs": 2.38,
      "origincontinent": "United States",
      "destinationcontinent": "Asia",
      "callergender": "Male",
      "recipientgender": "Female"
    },
    {
      "caller": "Ida",
      "start": "27.09.2013 02:14:47",
      "end": "27.09.2013 02:20:47",
      "duration": 6,
      "recipient": "Sidney",
      "origin": "Maine",
      "destination": "Mayotte Island",
      "ratepermin": 1,
      "costs": 6,
      "origincontinent": "United States",
      "destinationcontinent": "Africa",
      "callergender": "Female",
      "recipientgender": "Male"
    },
    {
      "caller": "Ida",
      "start": "27.09.2013 02:14:47",
      "end": "27.09.2013 02:27:47",
      "duration": 13,
      "recipient": "Sidney",
      "origin": "Maine",
      "destination": "Mayotte Island",
      "ratepermin": 1,
      "costs": 13,
      "origincontinent": "United States",
      "destinationcontinent": "Africa",
      "callergender": "Female",
      "recipientgender": "Male"
    },
    {
      "caller": "Ida",
      "start": "27.09.2013 02:14:58",
      "end": "27.09.2013 02:56:58",
      "duration": 42,
      "recipient": "Sidney",
      "origin": "Maine",
      "destination": "Mayotte Island",
      "ratepermin": 1,
      "costs": 42,
      "origincontinent": "United States",
      "destinationcontinent": "Africa",
      "callergender": "Female",
      "recipientgender": "Male"
    },
    {
      "caller": "Ida",
      "start": "27.09.2013 02:14:58",
      "end": "27.09.2013 03:21:58",
      "duration": 67,
      "recipient": "Sidney",
      "origin": "Maine",
      "destination": "Mayotte Island",
      "ratepermin": 1,
      "costs": 67,
      "origincontinent": "United States",
      "destinationcontinent": "Africa",
      "callergender": "Female",
      "recipientgender": "Male"
    },
    {
      "caller": "Ida",
      "start": "27.09.2013 02:15:44",
      "end": "27.09.2013 02:43:44",
      "duration": 28,
      "recipient": "Sidney",
      "origin": "Maine",
      "destination": "Mayotte Island",
      "ratepermin": 1,
      "costs": 28,
      "origincontinent": "United States",
      "destinationcontinent": "Africa",
      "callergender": "Female",
      "recipientgender": "Male"
    },
    {
      "caller": "Ida",
      "start": "27.09.2013 02:15:44",
      "end": "27.09.2013 02:24:44",
      "duration": 9,
      "recipient": "Sidney",
      "origin": "Maine",
      "destination": "Mayotte Island",
      "ratepermin": 1,
      "costs": 9,
      "origincontinent": "United States",
      "destinationcontinent": "Africa",
      "callergender": "Female",
      "recipientgender": "Male"
    },
    {
      "caller": "Clara",
      "start": "27.09.2013 02:16:07",
      "end": "27.09.2013 02:22:07",
      "duration": 6,
      "recipient": "Malia",
      "origin": "Maryland",
      "destination": "Monaco",
      "ratepermin": 0.14,
      "costs": 0.84,
      "origincontinent": "United States",
      "destinationcontinent": "Europe",
      "callergender": "Female",
      "recipientgender": "Female"
    },
    {
      "caller": "Jonathan",
      "start": "27.09.2013 02:16:07",
      "end": "27.09.2013 02:22:07",
      "duration": 6,
      "recipient": "Malia",
      "origin": "West Virginia",
      "destination": "Monaco",
      "ratepermin": 0.14,
      "costs": 0.84,
      "origincontinent": "United States",
      "destinationcontinent": "Europe",
      "callergender": "Male",
      "recipientgender": "Female"
    },
    {
      "caller": "Leni",
      "start": "27.09.2013 02:19:29",
      "end": "27.09.2013 04:08:29",
      "duration": 109,
      "recipient": "Matthias",
      "origin": "Missouri",
      "destination": "Mali Republic",
      "ratepermin": 1.03,
      "costs": 112.27,
      "origincontinent": "United States",
      "destinationcontinent": "Africa",
      "callergender": "Male",
      "recipientgender": "Male"
    },
    {
      "caller": "Paul",
      "start": "27.09.2013 02:21:34",
      "end": "27.09.2013 02:49:34",
      "duration": 28,
      "recipient": "Jasmin",
      "origin": "Montana",
      "destination": "Mauritius",
      "ratepermin": 1.22,
      "costs": 34.16,
      "origincontinent": "United States",
      "destinationcontinent": "Africa",
      "callergender": "Male",
      "recipientgender": "Female"
    },
    {
      "caller": "Leni",
      "start": "27.09.2013 02:23:15",
      "end": "27.09.2013 02:47:15",
      "duration": 24,
      "recipient": "Henriette",
      "origin": "Missouri",
      "destination": "Zimbabwe",
      "ratepermin": 0.48,
      "costs": 11.52,
      "origincontinent": "United States",
      "destinationcontinent": "Africa",
      "callergender": "Male",
      "recipientgender": "Female"
    },
    {
      "caller": "Ben",
      "start": "27.09.2013 02:23:37",
      "end": "27.09.2013 02:37:37",
      "duration": 14,
      "recipient": "Jasmin",
      "origin": "South Dakota",
      "destination": "Mauritius",
      "ratepermin": 1.22,
      "costs": 17.08,
      "origincontinent": "United States",
      "destinationcontinent": "Africa",
      "callergender": "Male",
      "recipientgender": "Female"
    },
    {
      "caller": "Ben",
      "start": "27.09.2013 02:24:15",
      "end": "27.09.2013 02:43:15",
      "duration": 19,
      "recipient": "Hugo",
      "origin": "South Dakota",
      "destination": "Zimbabwe",
      "ratepermin": 0.48,
      "costs": 9.12,
      "origincontinent": "United States",
      "destinationcontinent": "Africa",
      "callergender": "Male",
      "recipientgender": "Male"
    },
    {
      "caller": "Ben",
      "start": "27.09.2013 02:25:12",
      "end": "27.09.2013 03:12:12",
      "duration": 47,
      "recipient": "Diana",
      "origin": "South Dakota",
      "destination": "Falkland Islands",
      "ratepermin": 0.45,
      "costs": 21.15,
      "origincontinent": "United States",
      "destinationcontinent": "South America",
      "callergender": "Male",
      "recipientgender": "Female"
    },
    {
      "caller": "Ben",
      "start": "27.09.2013 02:26:58",
      "end": "27.09.2013 04:15:58",
      "duration": 109,
      "recipient": "Diana",
      "origin": "South Dakota",
      "destination": "Falkland Islands",
      "ratepermin": 0.45,
      "costs": 49.05,
      "origincontinent": "United States",
      "destinationcontinent": "South America",
      "callergender": "Male",
      "recipientgender": "Female"
    },
    {
      "caller": "Max",
      "start": "27.09.2013 02:31:48",
      "end": "27.09.2013 03:04:48",
      "duration": 33,
      "recipient": "Diana",
      "origin": "Ohio",
      "destination": "Falkland Islands",
      "ratepermin": 0.45,
      "costs": 14.85,
      "origincontinent": "United States",
      "destinationcontinent": "South America",
      "callergender": "Male",
      "recipientgender": "Female"
    },
    {
      "caller": "Clara",
      "start": "27.09.2013 02:36:52",
      "end": "27.09.2013 03:30:52",
      "duration": 54,
      "recipient": "Jasmin",
      "origin": "Maryland",
      "destination": "Mauritius",
      "ratepermin": 1.22,
      "costs": 65.88,
      "origincontinent": "United States",
      "destinationcontinent": "Africa",
      "callergender": "Female",
      "recipientgender": "Female"
    },
    {
      "caller": "Jonathan",
      "start": "27.09.2013 02:36:52",
      "end": "27.09.2013 03:30:52",
      "duration": 54,
      "recipient": "Jasmin",
      "origin": "West Virginia",
      "destination": "Mauritius",
      "ratepermin": 1.22,
      "costs": 65.88,
      "origincontinent": "United States",
      "destinationcontinent": "Africa",
      "callergender": "Male",
      "recipientgender": "Female"
    },
    {
      "caller": "Emma",
      "start": "27.09.2013 02:37:56",
      "end": "27.09.2013 02:38:56",
      "duration": 1,
      "recipient": "Jasmin",
      "origin": "New Jersey",
      "destination": "Mauritius",
      "ratepermin": 1.22,
      "costs": 1.22,
      "origincontinent": "United States",
      "destinationcontinent": "Africa",
      "callergender": "Female",
      "recipientgender": "Female"
    },
    {
      "caller": "Clara",
      "start": "27.09.2013 02:38:38",
      "end": "27.09.2013 03:32:38",
      "duration": 54,
      "recipient": "Jordan",
      "origin": "Maryland",
      "destination": "Bosnia",
      "ratepermin": 0.34,
      "costs": 18.36,
      "origincontinent": "United States",
      "destinationcontinent": "Europe",
      "callergender": "Female",
      "recipientgender": "Male"
    },
    {
      "caller": "Jonathan",
      "start": "27.09.2013 02:38:38",
      "end": "27.09.2013 04:31:38",
      "duration": 113,
      "recipient": "Diana",
      "origin": "West Virginia",
      "destination": "Falkland Islands",
      "ratepermin": 0.45,
      "costs": 50.85,
      "origincontinent": "United States",
      "destinationcontinent": "South America",
      "callergender": "Male",
      "recipientgender": "Female"
    },
    {
      "caller": "Paul",
      "start": "27.09.2013 02:38:50",
      "end": "27.09.2013 02:53:50",
      "duration": 15,
      "recipient": "Frauke",
      "origin": "Montana",
      "destination": "French Antilles",
      "ratepermin": 0.62,
      "costs": 9.3,
      "origincontinent": "United States",
      "destinationcontinent": "South America",
      "callergender": "Male",
      "recipientgender": "Female"
    },
    {
      "caller": "Emma",
      "start": "27.09.2013 02:38:50",
      "end": "27.09.2013 02:50:50",
      "duration": 12,
      "recipient": "Jasmin",
      "origin": "New Jersey",
      "destination": "Mauritius",
      "ratepermin": 1.22,
      "costs": 14.64,
      "origincontinent": "United States",
      "destinationcontinent": "Africa",
      "callergender": "Female",
      "recipientgender": "Female"
    },
    {
      "caller": "Emma",
      "start": "27.09.2013 02:39:26",
      "end": "27.09.2013 03:05:26",
      "duration": 26,
      "recipient": "Jasmin",
      "origin": "New Jersey",
      "destination": "Mauritius",
      "ratepermin": 1.22,
      "costs": 31.72,
      "origincontinent": "United States",
      "destinationcontinent": "Africa",
      "callergender": "Female",
      "recipientgender": "Female"
    },
    {
      "caller": "Ida",
      "start": "27.09.2013 02:39:49",
      "end": "27.09.2013 03:39:49",
      "duration": 60,
      "recipient": "Jayden",
      "origin": "Maine",
      "destination": "Kiribati",
      "ratepermin": 1.16,
      "costs": 69.6,
      "origincontinent": "United States",
      "destinationcontinent": "Oceania",
      "callergender": "Female",
      "recipientgender": "Male"
    },
    {
      "caller": "Paul",
      "start": "27.09.2013 02:40:06",
      "end": "27.09.2013 03:44:06",
      "duration": 64,
      "recipient": "Frauke",
      "origin": "Montana",
      "destination": "French Antilles",
      "ratepermin": 0.62,
      "costs": 39.68,
      "origincontinent": "United States",
      "destinationcontinent": "South America",
      "callergender": "Male",
      "recipientgender": "Female"
    },
    {
      "caller": "Clara",
      "start": "27.09.2013 02:42:13",
      "end": "27.09.2013 02:48:13",
      "duration": 6,
      "recipient": "Jordan",
      "origin": "Maryland",
      "destination": "Bosnia",
      "ratepermin": 0.34,
      "costs": 2.04,
      "origincontinent": "United States",
      "destinationcontinent": "Europe",
      "callergender": "Female",
      "recipientgender": "Male"
    },
    {
      "caller": "Jonathan",
      "start": "27.09.2013 02:42:13",
      "end": "27.09.2013 04:14:13",
      "duration": 92,
      "recipient": "Diana",
      "origin": "West Virginia",
      "destination": "Falkland Islands",
      "ratepermin": 0.45,
      "costs": 41.4,
      "origincontinent": "United States",
      "destinationcontinent": "South America",
      "callergender": "Male",
      "recipientgender": "Female"
    },
    {
      "caller": "Ida",
      "start": "27.09.2013 02:47:35",
      "end": "27.09.2013 03:54:35",
      "duration": 67,
      "recipient": "Ylvi",
      "origin": "Maine",
      "destination": "Anguilla",
      "ratepermin": 0.57,
      "costs": 38.19,
      "origincontinent": "United States",
      "destinationcontinent": "South America",
      "callergender": "Female",
      "recipientgender": "Female"
    },
    {
      "caller": "Ida",
      "start": "27.09.2013 02:47:35",
      "end": "27.09.2013 04:23:35",
      "duration": 96,
      "recipient": "Ylvi",
      "origin": "Maine",
      "destination": "Anguilla",
      "ratepermin": 0.57,
      "costs": 54.72,
      "origincontinent": "United States",
      "destinationcontinent": "South America",
      "callergender": "Female",
      "recipientgender": "Female"
    },
    {
      "caller": "Leni",
      "start": "27.09.2013 02:49:37",
      "end": "27.09.2013 04:19:37",
      "duration": 90,
      "recipient": "Henriette",
      "origin": "Missouri",
      "destination": "Zimbabwe",
      "ratepermin": 0.48,
      "costs": 43.2,
      "origincontinent": "United States",
      "destinationcontinent": "Africa",
      "callergender": "Male",
      "recipientgender": "Female"
    },
    {
      "caller": "Leni",
      "start": "27.09.2013 02:51:42",
      "end": "27.09.2013 04:14:42",
      "duration": 83,
      "recipient": "Anni",
      "origin": "Missouri",
      "destination": "Cayman Islands",
      "ratepermin": 0.24,
      "costs": 19.92,
      "origincontinent": "United States",
      "destinationcontinent": "Oceania",
      "callergender": "Male",
      "recipientgender": "Female"
    },
    {
      "caller": "Emma",
      "start": "27.09.2013 02:53:54",
      "end": "27.09.2013 04:14:54",
      "duration": 81,
      "recipient": "Diana",
      "origin": "New Jersey",
      "destination": "Falkland Islands",
      "ratepermin": 0.45,
      "costs": 36.45,
      "origincontinent": "United States",
      "destinationcontinent": "South America",
      "callergender": "Female",
      "recipientgender": "Female"
    },
    {
      "caller": "Clara",
      "start": "27.09.2013 02:59:43",
      "end": "27.09.2013 04:02:43",
      "duration": 63,
      "recipient": "Jordan",
      "origin": "Maryland",
      "destination": "Bosnia",
      "ratepermin": 0.34,
      "costs": 21.42,
      "origincontinent": "United States",
      "destinationcontinent": "Europe",
      "callergender": "Female",
      "recipientgender": "Male"
    },
    {
      "caller": "Jonathan",
      "start": "27.09.2013 02:59:43",
      "end": "27.09.2013 04:02:43",
      "duration": 63,
      "recipient": "Diana",
      "origin": "West Virginia",
      "destination": "Falkland Islands",
      "ratepermin": 0.45,
      "costs": 28.35,
      "origincontinent": "United States",
      "destinationcontinent": "South America",
      "callergender": "Male",
      "recipientgender": "Female"
    },
    {
      "caller": "Paul",
      "start": "27.09.2013 03:07:57",
      "end": "27.09.2013 03:27:57",
      "duration": 20,
      "recipient": "Patrick",
      "origin": "Montana",
      "destination": "Colombia",
      "ratepermin": 0.19,
      "costs": 3.8,
      "origincontinent": "United States",
      "destinationcontinent": "South America",
      "callergender": "Male",
      "recipientgender": "Male"
    },
    {
      "caller": "Paul",
      "start": "27.09.2013 03:08:45",
      "end": "27.09.2013 03:45:45",
      "duration": 37,
      "recipient": "Frauke",
      "origin": "Montana",
      "destination": "French Antilles",
      "ratepermin": 0.62,
      "costs": 22.94,
      "origincontinent": "United States",
      "destinationcontinent": "South America",
      "callergender": "Male",
      "recipientgender": "Female"
    },
    {
      "caller": "Clara",
      "start": "27.09.2013 03:11:50",
      "end": "27.09.2013 04:50:50",
      "duration": 99,
      "recipient": "Jordan",
      "origin": "Maryland",
      "destination": "Bosnia",
      "ratepermin": 0.34,
      "costs": 33.66,
      "origincontinent": "United States",
      "destinationcontinent": "Europe",
      "callergender": "Female",
      "recipientgender": "Male"
    },
    {
      "caller": "Jonathan",
      "start": "27.09.2013 03:11:50",
      "end": "27.09.2013 04:50:50",
      "duration": 99,
      "recipient": "Diana",
      "origin": "West Virginia",
      "destination": "Falkland Islands",
      "ratepermin": 0.45,
      "costs": 44.55,
      "origincontinent": "United States",
      "destinationcontinent": "South America",
      "callergender": "Male",
      "recipientgender": "Female"
    },
    {
      "caller": "Paul",
      "start": "27.09.2013 03:16:09",
      "end": "27.09.2013 03:45:09",
      "duration": 29,
      "recipient": "Elif",
      "origin": "Montana",
      "destination": "Burundi",
      "ratepermin": 1.39,
      "costs": 40.31,
      "origincontinent": "United States",
      "destinationcontinent": "Africa",
      "callergender": "Male",
      "recipientgender": "Female"
    },
    {
      "caller": "Ben",
      "start": "27.09.2013 03:16:17",
      "end": "27.09.2013 04:09:17",
      "duration": 53,
      "recipient": "Talea",
      "origin": "South Dakota",
      "destination": "Denmark",
      "ratepermin": 0.08,
      "costs": 4.24,
      "origincontinent": "United States",
      "destinationcontinent": "Europe",
      "callergender": "Male",
      "recipientgender": "Female"
    },
    {
      "caller": "Paul",
      "start": "27.09.2013 03:47:32",
      "end": "27.09.2013 04:11:32",
      "duration": 24,
      "recipient": "Stina",
      "origin": "Montana",
      "destination": "Mexico",
      "ratepermin": 0.07,
      "costs": 1.68,
      "origincontinent": "United States",
      "destinationcontinent": "North America",
      "callergender": "Male",
      "recipientgender": "Female"
    },
    {
      "caller": "Ben",
      "start": "27.09.2013 05:08:06",
      "end": "27.09.2013 06:28:06",
      "duration": 80,
      "recipient": "Hugo",
      "origin": "South Dakota",
      "destination": "Zimbabwe",
      "ratepermin": 0.48,
      "costs": 38.4,
      "origincontinent": "United States",
      "destinationcontinent": "Africa",
      "callergender": "Male",
      "recipientgender": "Male"
    },
    {
      "caller": "Ben",
      "start": "27.09.2013 05:24:38",
      "end": "27.09.2013 05:35:38",
      "duration": 11,
      "recipient": "Diana",
      "origin": "South Dakota",
      "destination": "Falkland Islands",
      "ratepermin": 0.45,
      "costs": 4.95,
      "origincontinent": "United States",
      "destinationcontinent": "South America",
      "callergender": "Male",
      "recipientgender": "Female"
    },
    {
      "caller": "Ben",
      "start": "27.09.2013 11:41:36",
      "end": "27.09.2013 12:17:36",
      "duration": 36,
      "recipient": "Diana",
      "origin": "South Dakota",
      "destination": "Falkland Islands",
      "ratepermin": 0.45,
      "costs": 16.2,
      "origincontinent": "United States",
      "destinationcontinent": "South America",
      "callergender": "Male",
      "recipientgender": "Female"
    },
    {
      "caller": "Ben",
      "start": "27.09.2013 11:44:26",
      "end": "27.09.2013 12:17:26",
      "duration": 33,
      "recipient": "Diana",
      "origin": "South Dakota",
      "destination": "Falkland Islands",
      "ratepermin": 0.45,
      "costs": 14.85,
      "origincontinent": "United States",
      "destinationcontinent": "South America",
      "callergender": "Male",
      "recipientgender": "Female"
    },
    {
      "caller": "Ben",
      "start": "27.09.2013 11:46:02",
      "end": "27.09.2013 12:00:02",
      "duration": 14,
      "recipient": "Diana",
      "origin": "South Dakota",
      "destination": "Falkland Islands",
      "ratepermin": 0.45,
      "costs": 6.3,
      "origincontinent": "United States",
      "destinationcontinent": "South America",
      "callergender": "Male",
      "recipientgender": "Female"
    },
    {
      "caller": "Leni",
      "start": "27.09.2013 13:35:27",
      "end": "27.09.2013 13:58:27",
      "duration": 23,
      "recipient": "Medina",
      "origin": "Missouri",
      "destination": "Hong Kong",
      "ratepermin": 0.09,
      "costs": 2.07,
      "origincontinent": "United States",
      "destinationcontinent": "Asia",
      "callergender": "Male",
      "recipientgender": "Female"
    },
    {
      "caller": "Ida",
      "start": "27.09.2013 13:37:29",
      "end": "27.09.2013 14:09:29",
      "duration": 32,
      "recipient": "Valentin",
      "origin": "Maine",
      "destination": "Pakistan",
      "ratepermin": 0.36,
      "costs": 11.52,
      "origincontinent": "United States",
      "destinationcontinent": "Asia",
      "callergender": "Female",
      "recipientgender": "Male"
    },
    {
      "caller": "Ida",
      "start": "27.09.2013 13:37:29",
      "end": "27.09.2013 14:53:29",
      "duration": 76,
      "recipient": "Valentin",
      "origin": "Maine",
      "destination": "Pakistan",
      "ratepermin": 0.36,
      "costs": 27.36,
      "origincontinent": "United States",
      "destinationcontinent": "Asia",
      "callergender": "Female",
      "recipientgender": "Male"
    },
    {
      "caller": "Leni",
      "start": "27.09.2013 13:44:47",
      "end": "27.09.2013 13:59:47",
      "duration": 15,
      "recipient": "Medina",
      "origin": "Missouri",
      "destination": "Hong Kong",
      "ratepermin": 0.09,
      "costs": 1.35,
      "origincontinent": "United States",
      "destinationcontinent": "Asia",
      "callergender": "Male",
      "recipientgender": "Female"
    },
    {
      "caller": "Leni",
      "start": "27.09.2013 13:58:06",
      "end": "27.09.2013 14:50:06",
      "duration": 52,
      "recipient": "Christopher",
      "origin": "Missouri",
      "destination": "Germany",
      "ratepermin": 0.07,
      "costs": 3.64,
      "origincontinent": "United States",
      "destinationcontinent": "Europe",
      "callergender": "Male",
      "recipientgender": "Male"
    },
    {
      "caller": "Clara",
      "start": "27.09.2013 14:06:40",
      "end": "27.09.2013 14:53:40",
      "duration": 47,
      "recipient": "Jordan",
      "origin": "Maryland",
      "destination": "Bosnia",
      "ratepermin": 0.34,
      "costs": 15.98,
      "origincontinent": "United States",
      "destinationcontinent": "Europe",
      "callergender": "Female",
      "recipientgender": "Male"
    },
    {
      "caller": "Jonathan",
      "start": "27.09.2013 14:06:40",
      "end": "27.09.2013 14:53:40",
      "duration": 47,
      "recipient": "Diana",
      "origin": "West Virginia",
      "destination": "Falkland Islands",
      "ratepermin": 0.45,
      "costs": 21.15,
      "origincontinent": "United States",
      "destinationcontinent": "South America",
      "callergender": "Male",
      "recipientgender": "Female"
    },
    {
      "caller": "Leni",
      "start": "27.09.2013 14:08:34",
      "end": "27.09.2013 14:55:34",
      "duration": 47,
      "recipient": "Christopher",
      "origin": "Missouri",
      "destination": "Germany",
      "ratepermin": 0.07,
      "costs": 3.29,
      "origincontinent": "United States",
      "destinationcontinent": "Europe",
      "callergender": "Male",
      "recipientgender": "Male"
    },
    {
      "caller": "Leni",
      "start": "27.09.2013 14:08:42",
      "end": "27.09.2013 14:33:42",
      "duration": 25,
      "recipient": "Medina",
      "origin": "Missouri",
      "destination": "Hong Kong",
      "ratepermin": 0.09,
      "costs": 2.25,
      "origincontinent": "United States",
      "destinationcontinent": "Asia",
      "callergender": "Male",
      "recipientgender": "Female"
    },
    {
      "caller": "Leni",
      "start": "27.09.2013 14:13:24",
      "end": "27.09.2013 14:44:24",
      "duration": 31,
      "recipient": "Medina",
      "origin": "Missouri",
      "destination": "Hong Kong",
      "ratepermin": 0.09,
      "costs": 2.79,
      "origincontinent": "United States",
      "destinationcontinent": "Asia",
      "callergender": "Male",
      "recipientgender": "Female"
    },
    {
      "caller": "Leni",
      "start": "27.09.2013 14:15:51",
      "end": "27.09.2013 14:25:51",
      "duration": 10,
      "recipient": "Diana",
      "origin": "Missouri",
      "destination": "Falkland Islands",
      "ratepermin": 0.45,
      "costs": 4.5,
      "origincontinent": "United States",
      "destinationcontinent": "South America",
      "callergender": "Male",
      "recipientgender": "Female"
    },
    {
      "caller": "Clara",
      "start": "27.09.2013 15:16:24",
      "end": "27.09.2013 17:00:24",
      "duration": 104,
      "recipient": "Jordan",
      "origin": "Maryland",
      "destination": "Bosnia",
      "ratepermin": 0.34,
      "costs": 35.36,
      "origincontinent": "United States",
      "destinationcontinent": "Europe",
      "callergender": "Female",
      "recipientgender": "Male"
    },
    {
      "caller": "Jonathan",
      "start": "27.09.2013 15:16:24",
      "end": "27.09.2013 15:36:24",
      "duration": 20,
      "recipient": "Diana",
      "origin": "West Virginia",
      "destination": "Falkland Islands",
      "ratepermin": 0.45,
      "costs": 9,
      "origincontinent": "United States",
      "destinationcontinent": "South America",
      "callergender": "Male",
      "recipientgender": "Female"
    },
    {
      "caller": "Ben",
      "start": "27.09.2013 16:45:27",
      "end": "27.09.2013 17:16:27",
      "duration": 31,
      "recipient": "Diana",
      "origin": "South Dakota",
      "destination": "Falkland Islands",
      "ratepermin": 0.45,
      "costs": 13.95,
      "origincontinent": "United States",
      "destinationcontinent": "South America",
      "callergender": "Male",
      "recipientgender": "Female"
    },
    {
      "caller": "Leni",
      "start": "27.09.2013 16:56:35",
      "end": "27.09.2013 17:04:35",
      "duration": 8,
      "recipient": "Medina",
      "origin": "Missouri",
      "destination": "Hong Kong",
      "ratepermin": 0.09,
      "costs": 0.72,
      "origincontinent": "United States",
      "destinationcontinent": "Asia",
      "callergender": "Male",
      "recipientgender": "Female"
    },
    {
      "caller": "Leni",
      "start": "27.09.2013 16:57:51",
      "end": "27.09.2013 17:04:51",
      "duration": 7,
      "recipient": "Medina",
      "origin": "Missouri",
      "destination": "Hong Kong",
      "ratepermin": 0.09,
      "costs": 0.63,
      "origincontinent": "United States",
      "destinationcontinent": "Asia",
      "callergender": "Male",
      "recipientgender": "Female"
    },
    {
      "caller": "Leni",
      "start": "27.09.2013 17:17:28",
      "end": "27.09.2013 18:54:28",
      "duration": 97,
      "recipient": "Medina",
      "origin": "Missouri",
      "destination": "Hong Kong",
      "ratepermin": 0.09,
      "costs": 8.73,
      "origincontinent": "United States",
      "destinationcontinent": "Asia",
      "callergender": "Male",
      "recipientgender": "Female"
    },
    {
      "caller": "Clara",
      "start": "27.09.2013 17:27:58",
      "end": "27.09.2013 18:07:58",
      "duration": 40,
      "recipient": "Jordan",
      "origin": "Maryland",
      "destination": "Bosnia",
      "ratepermin": 0.34,
      "costs": 13.6,
      "origincontinent": "United States",
      "destinationcontinent": "Europe",
      "callergender": "Female",
      "recipientgender": "Male"
    },
    {
      "caller": "Jonathan",
      "start": "27.09.2013 17:27:58",
      "end": "27.09.2013 19:18:58",
      "duration": 111,
      "recipient": "Diana",
      "origin": "West Virginia",
      "destination": "Falkland Islands",
      "ratepermin": 0.45,
      "costs": 49.95,
      "origincontinent": "United States",
      "destinationcontinent": "South America",
      "callergender": "Male",
      "recipientgender": "Female"
    },
    {
      "caller": "Leni",
      "start": "27.09.2013 17:48:25",
      "end": "27.09.2013 18:18:25",
      "duration": 30,
      "recipient": "Diana",
      "origin": "Missouri",
      "destination": "Falkland Islands",
      "ratepermin": 0.45,
      "costs": 13.5,
      "origincontinent": "United States",
      "destinationcontinent": "South America",
      "callergender": "Male",
      "recipientgender": "Female"
    },
    {
      "caller": "Ben",
      "start": "27.09.2013 18:59:24",
      "end": "27.09.2013 19:57:24",
      "duration": 58,
      "recipient": "Adelina",
      "origin": "South Dakota",
      "destination": "Mauritania",
      "ratepermin": 0.98,
      "costs": 56.84,
      "origincontinent": "United States",
      "destinationcontinent": "Africa",
      "callergender": "Male",
      "recipientgender": "Female"
    },
    {
      "caller": "Leni",
      "start": "27.09.2013 19:01:19",
      "end": "27.09.2013 19:07:19",
      "duration": 6,
      "recipient": "Medina",
      "origin": "Missouri",
      "destination": "Hong Kong",
      "ratepermin": 0.09,
      "costs": 0.54,
      "origincontinent": "United States",
      "destinationcontinent": "Asia",
      "callergender": "Male",
      "recipientgender": "Female"
    },
    {
      "caller": "Leni",
      "start": "27.09.2013 19:01:31",
      "end": "27.09.2013 19:34:31",
      "duration": 33,
      "recipient": "Medina",
      "origin": "Missouri",
      "destination": "Hong Kong",
      "ratepermin": 0.09,
      "costs": 2.97,
      "origincontinent": "United States",
      "destinationcontinent": "Asia",
      "callergender": "Male",
      "recipientgender": "Female"
    },
    {
      "caller": "Max",
      "start": "27.09.2013 19:14:35",
      "end": "27.09.2013 19:52:35",
      "duration": 38,
      "recipient": "Diana",
      "origin": "Ohio",
      "destination": "Falkland Islands",
      "ratepermin": 0.45,
      "costs": 17.1,
      "origincontinent": "United States",
      "destinationcontinent": "South America",
      "callergender": "Male",
      "recipientgender": "Female"
    },
    {
      "caller": "Ida",
      "start": "27.09.2013 19:51:48",
      "end": "27.09.2013 20:36:48",
      "duration": 45,
      "recipient": "Soraya",
      "origin": "Maine",
      "destination": "Algeria",
      "ratepermin": 0.48,
      "costs": 21.6,
      "origincontinent": "United States",
      "destinationcontinent": "Africa",
      "callergender": "Female",
      "recipientgender": "Female"
    },
    {
      "caller": "Ida",
      "start": "27.09.2013 19:51:48",
      "end": "27.09.2013 21:04:48",
      "duration": 73,
      "recipient": "Soraya",
      "origin": "Maine",
      "destination": "Algeria",
      "ratepermin": 0.48,
      "costs": 35.04,
      "origincontinent": "United States",
      "destinationcontinent": "Africa",
      "callergender": "Female",
      "recipientgender": "Female"
    },
    {
      "caller": "Ida",
      "start": "27.09.2013 20:18:09",
      "end": "27.09.2013 20:21:09",
      "duration": 3,
      "recipient": "Elaine",
      "origin": "Maine",
      "destination": "Laos",
      "ratepermin": 2.39,
      "costs": 7.17,
      "origincontinent": "United States",
      "destinationcontinent": "Asia",
      "callergender": "Female",
      "recipientgender": "Female"
    },
    {
      "caller": "Ida",
      "start": "27.09.2013 20:18:09",
      "end": "27.09.2013 21:30:09",
      "duration": 72,
      "recipient": "Elaine",
      "origin": "Maine",
      "destination": "Laos",
      "ratepermin": 2.39,
      "costs": 172.08,
      "origincontinent": "United States",
      "destinationcontinent": "Asia",
      "callergender": "Female",
      "recipientgender": "Female"
    },
    {
      "caller": "Emma",
      "start": "27.09.2013 20:37:51",
      "end": "27.09.2013 21:20:51",
      "duration": 43,
      "recipient": "Diana",
      "origin": "New Jersey",
      "destination": "Falkland Islands",
      "ratepermin": 0.45,
      "costs": 19.35,
      "origincontinent": "United States",
      "destinationcontinent": "South America",
      "callergender": "Female",
      "recipientgender": "Female"
    },
    {
      "caller": "Emma",
      "start": "27.09.2013 21:20:14",
      "end": "27.09.2013 23:15:14",
      "duration": 115,
      "recipient": "Diana",
      "origin": "New Jersey",
      "destination": "Falkland Islands",
      "ratepermin": 0.45,
      "costs": 51.75,
      "origincontinent": "United States",
      "destinationcontinent": "South America",
      "callergender": "Female",
      "recipientgender": "Female"
    },
    {
      "caller": "Leni",
      "start": "27.09.2013 21:22:15",
      "end": "27.09.2013 21:29:15",
      "duration": 7,
      "recipient": "Medina",
      "origin": "Missouri",
      "destination": "Hong Kong",
      "ratepermin": 0.09,
      "costs": 0.63,
      "origincontinent": "United States",
      "destinationcontinent": "Asia",
      "callergender": "Male",
      "recipientgender": "Female"
    },
    {
      "caller": "Leni",
      "start": "27.09.2013 21:22:29",
      "end": "27.09.2013 21:27:29",
      "duration": 5,
      "recipient": "Medina",
      "origin": "Missouri",
      "destination": "Hong Kong",
      "ratepermin": 0.09,
      "costs": 0.45,
      "origincontinent": "United States",
      "destinationcontinent": "Asia",
      "callergender": "Male",
      "recipientgender": "Female"
    },
    {
      "caller": "Clara",
      "start": "27.09.2013 21:48:50",
      "end": "27.09.2013 21:57:50",
      "duration": 9,
      "recipient": "Jordan",
      "origin": "Maryland",
      "destination": "Bosnia",
      "ratepermin": 0.34,
      "costs": 3.06,
      "origincontinent": "United States",
      "destinationcontinent": "Europe",
      "callergender": "Female",
      "recipientgender": "Male"
    },
    {
      "caller": "Jonathan",
      "start": "27.09.2013 21:48:50",
      "end": "27.09.2013 22:23:50",
      "duration": 35,
      "recipient": "Diana",
      "origin": "West Virginia",
      "destination": "Falkland Islands",
      "ratepermin": 0.45,
      "costs": 15.75,
      "origincontinent": "United States",
      "destinationcontinent": "South America",
      "callergender": "Male",
      "recipientgender": "Female"
    },
    {
      "caller": "Leni",
      "start": "27.09.2013 23:47:49",
      "end": "28.09.2013 00:16:49",
      "duration": 29,
      "recipient": "Anthony",
      "origin": "Missouri",
      "destination": "Portugal",
      "ratepermin": 0.09,
      "costs": 2.61,
      "origincontinent": "United States",
      "destinationcontinent": "Europe",
      "callergender": "Male",
      "recipientgender": "Male"
    }
  ]
}